{
  "FormVersionId": "e64614ee-e24c-41cc-a7fa-2044f5e2b83b",
  "FormId": "f1111111-1111-1111-1111-111111111111",
  "ToolType": "ArtifactForms",
  "FormKey": "CSCI-Form",
  "VersionNumber": 3,
  "IsPublished": true,
  "PublishedDate": "2026-06-29T18:43:28.5504558Z",
  "Sections": [
    {
      "SectionId": "4f44ec9c-485b-4a7e-a6bd-797f4356e06b",
      "Title": "Custom Fields",
      "Order": 1,
      "Fields": [
        {
          "FieldId": "159348c1-88de-44b2-9a0b-d45266e9a057",
          "Type": "Text",
          "Label": "Custom text",
          "GridRow": 1,
          "GridColumn": 1,
          "GridSpan": 12,
          "Options": null,
          "AllowCustomValue": false,
          "Validation": {
            "Required": false,
            "MaxLength": 200,
            "RegexPattern": null,
            "Min": null,
            "Max": null
          },
          "ConditionalRules": null
        },
        {
          "FieldId": "7c610b1a-bb63-4b28-9c46-2bdbae03a429",
          "Type": "Number",
          "Label": "Custom number",
          "GridRow": 2,
          "GridColumn": 1,
          "GridSpan": 12,
          "Options": null,
          "AllowCustomValue": false,
          "Validation": {
            "Required": false,
            "MaxLength": null,
            "RegexPattern": null,
            "Min": 1,
            "Max": 100
          },
          "ConditionalRules": null
        },
        {
          "FieldId": "25dbc03b-efef-4e77-bcd4-3610d94d1a96",
          "Type": "Date",
          "Label": "Custom  date",
          "GridRow": 3,
          "GridColumn": 1,
          "GridSpan": 12,
          "Options": null,
          "AllowCustomValue": false,
          "Validation": null,
          "ConditionalRules": null
        },
        {
          "FieldId": "11944103-d2fb-4ae9-a0df-f113d7a1a2c7",
          "Type": "Dropdown",
          "Label": "Custom dropdown",
          "GridRow": 4,
          "GridColumn": 1,
          "GridSpan": 12,
          "Options": [
            {
              "Value": "option-a",
              "Label": "Option A"
            },
            {
              "Value": "option-b",
              "Label": "Option B"
            },
            {
              "Value": "option-c",
              "Label": "Option C"
            }
          ],
          "AllowCustomValue": false,
          "Validation": null,
          "ConditionalRules": null
        },
        {
          "FieldId": "f4aa1eec-db5e-4542-80eb-a5f85a8c4298",
          "Type": "MultiSelect",
          "Label": "custom multiselect",
          "GridRow": 6,
          "GridColumn": 1,
          "GridSpan": 12,
          "Options": [
            {
              "Value": "com1",
              "Label": "com1"
            },
            {
              "Value": "com2",
              "Label": "com2"
            },
            {
              "Value": "com3",
              "Label": "com3"
            },
            {
              "Value": "com4",
              "Label": "com4"
            }
          ],
          "AllowCustomValue": false,
          "Validation": null,
          "ConditionalRules": null
        }
      ]
    }
  ]
}